MANIFEST.in
README.rst
setup.py
django_passreset.egg-info/PKG-INFO
django_passreset.egg-info/SOURCES.txt
django_passreset.egg-info/dependency_links.txt
django_passreset.egg-info/top_level.txt
passreset/__init__.py
passreset/apps.py
passreset/forms.py
passreset/templates/passreset/base.html
passreset/templates/passreset/complete.html
passreset/templates/passreset/confirm.html
passreset/templates/passreset/done.html
passreset/templates/passreset/email.html
passreset/templates/passreset/reset_password.html
passreset/templates/passreset/subject.txt
passreset/templates/passreset/admin/login.html
passreset/templates/registration/password_reset_email.html