Metadata-Version: 1.1
Name: django-passreset
Version: 0.3
Summary: Easily add password reset workflows to your django project.
Home-page: http://github.com/bendavis78
Author: Ben Davis
Author-email: bendavis78@gmail.com
License: UNKNOWN
Keywords: django admin
Platform: UNKNOWN
Classifier: Development Status :: 4 - Beta
Classifier: Intended Audience :: Developers
Classifier: Operating System :: OS Independent
Classifier: Programming Language :: Python
Classifier: Topic :: Software Development :: Libraries :: Python Modules
